jinja2_fsloader/__init__.py
jinja2_fsloader/_version.txt
tests/__init__.py
tests/test_fsloader.py
tests/test_misc.py
tests/utils.py
jinja2_fsloader-0.3.0.dist-info/COPYING
jinja2_fsloader-0.3.0.dist-info/METADATA
jinja2_fsloader-0.3.0.dist-info/WHEEL
jinja2_fsloader-0.3.0.dist-info/top_level.txt
jinja2_fsloader-0.3.0.dist-info/zip-safe
jinja2_fsloader-0.3.0.dist-info/RECORD
