Metadata-Version: 2.1
Name: jinja2-fsloader
Version: 0.3.0
Summary: A Jinja2 template loader using PyFilesystem2
Home-page: https://github.com/althonos/jinja2-fsloader/
Author: Martin Larralde
Author-email: martin.larralde@ens-paris-saclay.fr
License: MIT
Project-URL: Bug Reports, https://github.com/althonos/jinja2-fsloader
Project-URL: Pyfilesystem2 documentation, https://docs.pyfilesystem.org
Keywords: jinja2,template,loader,pyfilesystem2,pyfilesystem,fs
Platform: any
Classifier: Development Status :: 4 - Beta
Classifier: Intended Audience :: Developers
Classifier: License :: OSI Approved :: MIT License
Classifier: Operating System :: OS Independent
Classifier: Programming Language :: Python
Classifier: Programming Language :: Python :: 2.7
Classifier: Programming Language :: Python :: 3.4
Classifier: Programming Language :: Python :: 3.5
Classifier: Programming Language :: Python :: 3.6
Classifier: Programming Language :: Python :: 3.7
Classifier: Topic :: Internet :: WWW/HTTP :: Dynamic Content
Classifier: Topic :: System :: Filesystems
Classifier: Topic :: Software Development :: Libraries :: Python Modules
Classifier: Topic :: Text Processing :: Markup :: HTML
Requires-Python: >= 2.7, != 3.0.*, != 3.1.*, != 3.2.*, != 3.3.*, != 3.5.1
Requires-Dist: fs (~=2.1)
Requires-Dist: jinja2 (~=2.0)
